numeral_tax/__init__.py
numeral_tax/_base_client.py
numeral_tax/_client.py
numeral_tax/_compat.py
numeral_tax/_constants.py
numeral_tax/_exceptions.py
numeral_tax/_files.py
numeral_tax/_models.py
numeral_tax/_qs.py
numeral_tax/_resource.py
numeral_tax/_response.py
numeral_tax/_streaming.py
numeral_tax/_types.py
numeral_tax/_version.py
numeral_tax/py.typed
numeral_tax/_utils/__init__.py
numeral_tax/_utils/_compat.py
numeral_tax/_utils/_datetime_parse.py
numeral_tax/_utils/_logs.py
numeral_tax/_utils/_proxy.py
numeral_tax/_utils/_reflection.py
numeral_tax/_utils/_resources_proxy.py
numeral_tax/_utils/_streams.py
numeral_tax/_utils/_sync.py
numeral_tax/_utils/_transform.py
numeral_tax/_utils/_typing.py
numeral_tax/_utils/_utils.py
numeral_tax/lib/.keep
numeral_tax/resources/__init__.py
numeral_tax/resources/tax/__init__.py
numeral_tax/resources/tax/calculations.py
numeral_tax/resources/tax/customers.py
numeral_tax/resources/tax/products.py
numeral_tax/resources/tax/refund_reversals.py
numeral_tax/resources/tax/refunds.py
numeral_tax/resources/tax/tax.py
numeral_tax/resources/tax/transactions/__init__.py
numeral_tax/resources/tax/transactions/refunds.py
numeral_tax/resources/tax/transactions/transactions.py
numeral_tax/types/__init__.py
numeral_tax/types/metadata.py
numeral_tax/types/metadata_param.py
numeral_tax/types/tax_ping_response.py
numeral_tax/types/shared/__init__.py
numeral_tax/types/shared/refund_response.py
numeral_tax/types/tax/__init__.py
numeral_tax/types/tax/calculation_create_params.py
numeral_tax/types/tax/calculation_response.py
numeral_tax/types/tax/customer_create_params.py
numeral_tax/types/tax/customer_delete_response.py
numeral_tax/types/tax/customer_response.py
numeral_tax/types/tax/delete_product_response.py
numeral_tax/types/tax/delete_transaction_response.py
numeral_tax/types/tax/product_create_params.py
numeral_tax/types/tax/product_list_params.py
numeral_tax/types/tax/product_list_response.py
numeral_tax/types/tax/product_response.py
numeral_tax-0.1.0a1.dist-info/METADATA
numeral_tax-0.1.0a1.dist-info/WHEEL
numeral_tax-0.1.0a1.dist-info/licenses/LICENSE
numeral_tax-0.1.0a1.dist-info/RECORD
